<annotation>
	<folder>JPEGImages</folder>
	<filename>3f9133e0-6e0d-4fe1-bc2c-8d22faf9af7d.jpg</filename>
	<path>D:\labelimg\helmets\JPEGImages\3f9133e0-6e0d-4fe1-bc2c-8d22faf9af7d.jpg</path>
	<source>
		<database>Unknown</database>
	</source>
	<size>
		<width>500</width>
		<height>500</height>
		<depth>3</depth>
	</size>
	<segmented>0</segmented>
	<object>
		<name>other_clothes</name>
		<pose>Unspecified</pose>
		<truncated>0</truncated>
		<difficult>0</difficult>
		<bndbox>
			<xmin>142</xmin>
			<ymin>151</ymin>
			<xmax>352</xmax>
			<ymax>453</ymax>
		</bndbox>
	</object>
	<object>
		<name>head</name>
		<pose>Unspecified</pose>
		<truncated>0</truncated>
		<difficult>0</difficult>
		<bndbox>
			<xmin>170</xmin>
			<ymin>20</ymin>
			<xmax>298</xmax>
			<ymax>182</ymax>
		</bndbox>
	</object>
</annotation>
