<annotation>
	<folder>1</folder>
	<filename>part2_000071.jpg</filename>
	<path>D:\labelimg\helmets1\1\part2_000071.jpg</path>
	<source>
		<database>Unknown</database>
	</source>
	<size>
		<width>1687</width>
		<height>1126</height>
		<depth>3</depth>
	</size>
	<segmented>0</segmented>
	<object>
		<name>helmet</name>
		<pose>Unspecified</pose>
		<truncated>0</truncated>
		<difficult>0</difficult>
		<bndbox>
			<xmin>918</xmin>
			<ymin>26</ymin>
			<xmax>1170</xmax>
			<ymax>314</ymax>
		</bndbox>
	</object>
	<object>
		<name>head</name>
		<pose>Unspecified</pose>
		<truncated>0</truncated>
		<difficult>0</difficult>
		<bndbox>
			<xmin>455</xmin>
			<ymin>103</ymin>
			<xmax>639</xmax>
			<ymax>368</ymax>
		</bndbox>
	</object>
	<object>
		<name>reflective_clothes</name>
		<pose>Unspecified</pose>
		<truncated>0</truncated>
		<difficult>0</difficult>
		<bndbox>
			<xmin>426</xmin>
			<ymin>332</ymin>
			<xmax>700</xmax>
			<ymax>861</ymax>
		</bndbox>
	</object>
	<object>
		<name>reflective_clothes</name>
		<pose>Unspecified</pose>
		<truncated>0</truncated>
		<difficult>0</difficult>
		<bndbox>
			<xmin>1141</xmin>
			<ymin>194</ymin>
			<xmax>1595</xmax>
			<ymax>675</ymax>
		</bndbox>
	</object>
</annotation>
