<annotation>
	<folder>JPEGImages - 副本</folder>
	<filename>part2_001916.jpg</filename>
	<path>D:\labelimg\helmets\JPEGImages - 副本\part2_001916.jpg</path>
	<source>
		<database>Unknown</database>
	</source>
	<size>
		<width>728</width>
		<height>485</height>
		<depth>3</depth>
	</size>
	<segmented>0</segmented>
	<object>
		<name>helmet</name>
		<pose>Unspecified</pose>
		<truncated>0</truncated>
		<difficult>0</difficult>
		<bndbox>
			<xmin>461</xmin>
			<ymin>60</ymin>
			<xmax>601</xmax>
			<ymax>227</ymax>
		</bndbox>
	</object>
	<object>
		<name>helmet</name>
		<pose>Unspecified</pose>
		<truncated>0</truncated>
		<difficult>0</difficult>
		<bndbox>
			<xmin>46</xmin>
			<ymin>126</ymin>
			<xmax>175</xmax>
			<ymax>269</ymax>
		</bndbox>
	</object>
	<object>
		<name>other_clothes</name>
		<pose>Unspecified</pose>
		<truncated>1</truncated>
		<difficult>0</difficult>
		<bndbox>
			<xmin>6</xmin>
			<ymin>249</ymin>
			<xmax>185</xmax>
			<ymax>485</ymax>
		</bndbox>
	</object>
	<object>
		<name>other_clothes</name>
		<pose>Unspecified</pose>
		<truncated>1</truncated>
		<difficult>0</difficult>
		<bndbox>
			<xmin>471</xmin>
			<ymin>203</ymin>
			<xmax>638</xmax>
			<ymax>485</ymax>
		</bndbox>
	</object>
</annotation>
