<annotation>
	<folder>JPEGImages</folder>
	<filename>1aab46af-428f-4ba1-8d76-33602d628b39.jpg</filename>
	<path>D:\labelimg\helmets\JPEGImages\1aab46af-428f-4ba1-8d76-33602d628b39.jpg</path>
	<source>
		<database>Unknown</database>
	</source>
	<size>
		<width>500</width>
		<height>683</height>
		<depth>3</depth>
	</size>
	<segmented>0</segmented>
	<object>
		<name>reflective_clothes</name>
		<pose>Unspecified</pose>
		<truncated>0</truncated>
		<difficult>0</difficult>
		<bndbox>
			<xmin>95</xmin>
			<ymin>209</ymin>
			<xmax>386</xmax>
			<ymax>590</ymax>
		</bndbox>
	</object>
	<object>
		<name>helmet</name>
		<pose>Unspecified</pose>
		<truncated>0</truncated>
		<difficult>0</difficult>
		<bndbox>
			<xmin>166</xmin>
			<ymin>50</ymin>
			<xmax>296</xmax>
			<ymax>228</ymax>
		</bndbox>
	</object>
</annotation>
