<annotation>
	<folder>JPEGImages</folder>
	<filename>a3996bd9-dbdf-4bd2-8b54-1ab13f1174fc.jpg</filename>
	<path>D:\labelimg\helmets\JPEGImages\a3996bd9-dbdf-4bd2-8b54-1ab13f1174fc.jpg</path>
	<source>
		<database>Unknown</database>
	</source>
	<size>
		<width>300</width>
		<height>200</height>
		<depth>3</depth>
	</size>
	<segmented>0</segmented>
	<object>
		<name>other_clothes</name>
		<pose>Unspecified</pose>
		<truncated>0</truncated>
		<difficult>0</difficult>
		<bndbox>
			<xmin>162</xmin>
			<ymin>45</ymin>
			<xmax>221</xmax>
			<ymax>111</ymax>
		</bndbox>
	</object>
	<object>
		<name>other_clothes</name>
		<pose>Unspecified</pose>
		<truncated>0</truncated>
		<difficult>0</difficult>
		<bndbox>
			<xmin>219</xmin>
			<ymin>36</ymin>
			<xmax>285</xmax>
			<ymax>96</ymax>
		</bndbox>
	</object>
	<object>
		<name>head</name>
		<pose>Unspecified</pose>
		<truncated>0</truncated>
		<difficult>0</difficult>
		<bndbox>
			<xmin>185</xmin>
			<ymin>29</ymin>
			<xmax>219</xmax>
			<ymax>52</ymax>
		</bndbox>
	</object>
	<object>
		<name>head</name>
		<pose>Unspecified</pose>
		<truncated>0</truncated>
		<difficult>0</difficult>
		<bndbox>
			<xmin>217</xmin>
			<ymin>13</ymin>
			<xmax>254</xmax>
			<ymax>38</ymax>
		</bndbox>
	</object>
</annotation>
