<annotation>
	<folder>JPEGImages - 副本</folder>
	<filename>part2_001614.jpg</filename>
	<path>D:\labelimg\helmets\JPEGImages - 副本\part2_001614.jpg</path>
	<source>
		<database>Unknown</database>
	</source>
	<size>
		<width>1050</width>
		<height>700</height>
		<depth>3</depth>
	</size>
	<segmented>0</segmented>
	<object>
		<name>helmet</name>
		<pose>Unspecified</pose>
		<truncated>0</truncated>
		<difficult>0</difficult>
		<bndbox>
			<xmin>87</xmin>
			<ymin>93</ymin>
			<xmax>266</xmax>
			<ymax>260</ymax>
		</bndbox>
	</object>
	<object>
		<name>helmet</name>
		<pose>Unspecified</pose>
		<truncated>0</truncated>
		<difficult>0</difficult>
		<bndbox>
			<xmin>527</xmin>
			<ymin>253</ymin>
			<xmax>590</xmax>
			<ymax>321</ymax>
		</bndbox>
	</object>
	<object>
		<name>helmet</name>
		<pose>Unspecified</pose>
		<truncated>0</truncated>
		<difficult>0</difficult>
		<bndbox>
			<xmin>619</xmin>
			<ymin>249</ymin>
			<xmax>742</xmax>
			<ymax>371</ymax>
		</bndbox>
	</object>
	<object>
		<name>helmet</name>
		<pose>Unspecified</pose>
		<truncated>0</truncated>
		<difficult>0</difficult>
		<bndbox>
			<xmin>716</xmin>
			<ymin>182</ymin>
			<xmax>804</xmax>
			<ymax>266</ymax>
		</bndbox>
	</object>
	<object>
		<name>helmet</name>
		<pose>Unspecified</pose>
		<truncated>0</truncated>
		<difficult>0</difficult>
		<bndbox>
			<xmin>837</xmin>
			<ymin>181</ymin>
			<xmax>911</xmax>
			<ymax>253</ymax>
		</bndbox>
	</object>
	<object>
		<name>helmet</name>
		<pose>Unspecified</pose>
		<truncated>0</truncated>
		<difficult>0</difficult>
		<bndbox>
			<xmin>812</xmin>
			<ymin>221</ymin>
			<xmax>849</xmax>
			<ymax>269</ymax>
		</bndbox>
	</object>
	<object>
		<name>helmet</name>
		<pose>Unspecified</pose>
		<truncated>0</truncated>
		<difficult>0</difficult>
		<bndbox>
			<xmin>907</xmin>
			<ymin>210</ymin>
			<xmax>952</xmax>
			<ymax>254</ymax>
		</bndbox>
	</object>
	<object>
		<name>helmet</name>
		<pose>Unspecified</pose>
		<truncated>0</truncated>
		<difficult>0</difficult>
		<bndbox>
			<xmin>960</xmin>
			<ymin>189</ymin>
			<xmax>1039</xmax>
			<ymax>261</ymax>
		</bndbox>
	</object>
	<object>
		<name>reflective_clothes</name>
		<pose>Unspecified</pose>
		<truncated>0</truncated>
		<difficult>0</difficult>
		<bndbox>
			<xmin>499</xmin>
			<ymin>318</ymin>
			<xmax>586</xmax>
			<ymax>470</ymax>
		</bndbox>
	</object>
	<object>
		<name>reflective_clothes</name>
		<pose>Unspecified</pose>
		<truncated>0</truncated>
		<difficult>0</difficult>
		<bndbox>
			<xmin>580</xmin>
			<ymin>375</ymin>
			<xmax>717</xmax>
			<ymax>603</ymax>
		</bndbox>
	</object>
	<object>
		<name>reflective_clothes</name>
		<pose>Unspecified</pose>
		<truncated>0</truncated>
		<difficult>0</difficult>
		<bndbox>
			<xmin>720</xmin>
			<ymin>268</ymin>
			<xmax>808</xmax>
			<ymax>464</ymax>
		</bndbox>
	</object>
	<object>
		<name>reflective_clothes</name>
		<pose>Unspecified</pose>
		<truncated>0</truncated>
		<difficult>0</difficult>
		<bndbox>
			<xmin>808</xmin>
			<ymin>251</ymin>
			<xmax>905</xmax>
			<ymax>417</ymax>
		</bndbox>
	</object>
	<object>
		<name>reflective_clothes</name>
		<pose>Unspecified</pose>
		<truncated>0</truncated>
		<difficult>0</difficult>
		<bndbox>
			<xmin>926</xmin>
			<ymin>251</ymin>
			<xmax>1040</xmax>
			<ymax>392</ymax>
		</bndbox>
	</object>
	<object>
		<name>reflective_clothes</name>
		<pose>Unspecified</pose>
		<truncated>0</truncated>
		<difficult>0</difficult>
		<bndbox>
			<xmin>905</xmin>
			<ymin>243</ymin>
			<xmax>943</xmax>
			<ymax>325</ymax>
		</bndbox>
	</object>
	<object>
		<name>other_clothes</name>
		<pose>Unspecified</pose>
		<truncated>0</truncated>
		<difficult>0</difficult>
		<bndbox>
			<xmin>95</xmin>
			<ymin>246</ymin>
			<xmax>322</xmax>
			<ymax>505</ymax>
		</bndbox>
	</object>
</annotation>
